eliud/__init__.py
eliud/__main__.py
eliud/apps/__init__.py
eliud/apps/config.py
eliud/apps/registry.py
eliud/commands/__init__.py
eliud/commands/exceptions.py
eliud/commands/generic/__init__.py
eliud/commands/generic/base.py
eliud/conf/__init__.py
eliud/conf/app_template/__init__.py-tpl
eliud/conf/app_template/apps.py-tpl
eliud/conf/app_template/commands.py-tpl
eliud/conf/app_template/markups.py-tpl
eliud/conf/app_template/migrations/__init__.py-tpl
eliud/conf/app_template/models.py-tpl
eliud/conf/app_template/tests.py-tpl
eliud/conf/global_settings.py
eliud/conf/locale/__init__.py
eliud/conf/project_template/apps/__init__.py-tpl
eliud/conf/project_template/manage.py-tpl
eliud/conf/project_template/project_name/settings.py-tpl
eliud/core/__init__.py
eliud/core/bot/__init__.py
eliud/core/checks/__init__.py
eliud/core/checks/messages.py
eliud/core/checks/registry.py
eliud/core/checks/security/__init__.py
eliud/core/checks/security/base.py
eliud/core/exceptions.py
eliud/core/mail/__init__.py
eliud/core/mail/message.py
eliud/core/mail/utils.py
eliud/core/management/__init__.py
eliud/core/management/base.py
eliud/core/management/color.py
eliud/core/management/commands/__init__.py
eliud/core/management/commands/runbot.py
eliud/core/management/commands/startapp.py
eliud/core/management/commands/startproject.py
eliud/core/management/templates.py
eliud/core/management/utils.py
eliud/core/serializers/__init__.py
eliud/core/servers/__init__.py
eliud/core/signals.py
eliud/db/__init__.py
eliud/db/migrations/__init__.py
eliud/db/migrations/executor.py
eliud/db/utils.py
eliud/dispatch/__init__.py
eliud/dispatch/dispatcher.py
eliud/markups/__init__.py
eliud/markups/base.py
eliud/middleware/__init__.py
eliud/template/__init__.py
eliud/template/autoreload.py
eliud/template/backends/__init__.py
eliud/template/backends/base.py
eliud/template/backends/eliud.py
eliud/template/base.py
eliud/template/context.py
eliud/template/defaulttags.py
eliud/template/engine.py
eliud-0.1.0.dist-info/entry_points.txt
eliud-0.1.0.dist-info/LICENSE
eliud-0.1.0.dist-info/WHEEL
eliud-0.1.0.dist-info/METADATA
eliud-0.1.0.dist-info/RECORD
